emonet_py/__init__.py
emonet_py/alexnet_big.py
emonet_py/check_data_files.py
emonet_py/convert_emonet_matlab_weights.py
emonet_py/demo.py
emonet_py/emonet.py
emonet_py/emonet_arousal.py
emonet_py/emonet_valence.py
emonet_py/test_integrity.py
emonet_py-1.0.8.dist-info/licenses/LICENSE.md
emonet_py-1.0.8.dist-info/METADATA
emonet_py-1.0.8.dist-info/WHEEL
emonet_py-1.0.8.dist-info/top_level.txt
emonet_py-1.0.8.dist-info/RECORD
