Metadata-Version: 2.4
Name: emonet-py
Version: 1.0.8
Summary: A PyTorch port of the MatLab EmoNet network by Kragel et al., 2019.
Author-email: Laurent Mertens <laurent.mertens@kuleuven.be>
Maintainer-email: Laurent Mertens <laurent.mertens@kuleuven.be>
License-Expression: MIT
Project-URL: Homepage, https://gitlab.com/EAVISE/lme/emonet
Project-URL: Changelog, https://gitlab.com/EAVISE/lme/emonet/blob/master/CHANGELOG.md
Keywords: ANN,PyTorch,Neural Networks,Emotion Recognition
Classifier: Programming Language :: Python
Classifier: Programming Language :: Python :: 3
Requires-Python: >=3.9
License-File: LICENSE.md
Requires-Dist: importlib_metadata>=7.1.0
Requires-Dist: python-gitlab>=4.6.0
Requires-Dist: Pillow>=9
Requires-Dist: torch>=2
Requires-Dist: torchvision>=0.15
Dynamic: license-file
